Metadata-Version: 2.1
Name: django-admin-anylogicfilter
Version: 0.1.3
Summary: Django app that adds admin filter with any functionality you need.
Home-page: https://github.com/mdncv/django-admin-anylogicfilter
Author: Maxim Medentsev
Author-email: m.v.medencev@gmail.com
Maintainer: Ivan Golyshev
Maintainer-email: golyshev.nomer@gmail.com
Classifier: Development Status :: 3 - Alpha
Classifier: Framework :: Django
Classifier: Intended Audience :: Developers
Classifier: License :: OSI Approved :: MIT License
Classifier: Programming Language :: Python :: 3
Classifier: Programming Language :: Python :: 3.6
Classifier: Programming Language :: Python :: 3.7
Classifier: Programming Language :: Python :: 3.8
Classifier: Programming Language :: Python :: 3.9
Classifier: Programming Language :: Python :: 3.10
Classifier: Programming Language :: Python :: 3.11
License-File: LICENSE
